ad_api/__init__.py
ad_api/auth.py
ad_api/client.py
ad_api/conf.py
ad_api/profiles.py
ad_api/common/__init__.py
ad_api/common/portfolios.py
ad_api/common/product_metadata.py
ad_api/common/profiles.py
ad_api/common/reports.py
ad_api/sp_brands/__init__.py
ad_api/sp_brands/adgroups.py
ad_api/sp_brands/ads.py
ad_api/sp_brands/bid_recommendations.py
ad_api/sp_brands/brands.py
ad_api/sp_brands/campaigns.py
ad_api/sp_brands/drafts.py
ad_api/sp_brands/keyword_recommendations.py
ad_api/sp_brands/keywords.py
ad_api/sp_brands/landing_page_asin.py
ad_api/sp_brands/media.py
ad_api/sp_brands/moderation.py
ad_api/sp_brands/negative_keywords.py
ad_api/sp_brands/negative_product_targeting.py
ad_api/sp_brands/product_targeting.py
ad_api/sp_brands/reports.py
ad_api/sp_brands/snapshots.py
ad_api/sp_brands/stores.py
ad_api/sp_brands/targeting_recommendations.py
ad_api/sp_display/__init__.py
ad_api/sp_display/adgroups.py
ad_api/sp_display/bid_recommendations.py
ad_api/sp_display/brand_safety_list.py
ad_api/sp_display/budget_rules.py
ad_api/sp_display/campaigns.py
ad_api/sp_display/creatives.py
ad_api/sp_display/negative_targeting.py
ad_api/sp_display/product_ads.py
ad_api/sp_display/reports.py
ad_api/sp_display/snapshots.py
ad_api/sp_display/suggest_products.py
ad_api/sp_display/targeting.py
ad_api/sp_display/targeting_recommendations.py
ad_api/sp_products/__init__.py
ad_api/sp_products/adgroups.py
ad_api/sp_products/bidrecommendations.py
ad_api/sp_products/budget_recommendations.py
ad_api/sp_products/budget_rules_recommendation.py
ad_api/sp_products/campaign_negative_keywords.py
ad_api/sp_products/campaigns.py
ad_api/sp_products/keywords.py
ad_api/sp_products/negative_keywords.py
ad_api/sp_products/negative_product_targeting.py
ad_api/sp_products/product_ads.py
ad_api/sp_products/product_targeting.py
ad_api/sp_products/reports.py
ad_api/sp_products/snapshots.py
ad_api/sp_products/suggested_keywords.py
tests/__init__.py
tests/test.py
tests/test_common.py
python_amazon_advertising_api-0.8.2.dist-info/LICENSE
python_amazon_advertising_api-0.8.2.dist-info/METADATA
python_amazon_advertising_api-0.8.2.dist-info/WHEEL
python_amazon_advertising_api-0.8.2.dist-info/top_level.txt
python_amazon_advertising_api-0.8.2.dist-info/RECORD
