Metadata-Version: 2.1
Name: python-amazon-advertising-api
Version: 0.8.2
Summary: Python wrapper for the Amazon Advertising API
Home-page: https://github.com/854350999/python-amazon-advertising-api
Author: WT
Author-email: 854350999@qq.com
License: MIT
Platform: UNKNOWN
License-File: LICENSE
Requires-Dist: requests
